README.rst
setup.cfg
setup.py
throwie/Throwie.py
throwie/__init__.py
throwie.egg-info/PKG-INFO
throwie.egg-info/SOURCES.txt
throwie.egg-info/dependency_links.txt
throwie.egg-info/entry_points.txt
throwie.egg-info/requires.txt
throwie.egg-info/top_level.txt
throwie/cli/__init__.py