Metadata-Version: 1.1
Name: throwie
Version: 1.0.0
Summary: Throwie - EC2 instances tagging tool
Home-page: https://github.com/b-b3rn4rd/throwie
Author: Bernard Baltrusaitis
Author-email: bernard@runawaylover.info
License: MIT
Keywords: ec2 tag boto3 cli
Platform: UNKNOWN
Classifier: Development Status :: 4 - Beta
Classifier: Intended Audience :: Developers
Classifier: Intended Audience :: System Administrators
Classifier: License :: OSI Approved :: MIT License
Classifier: Programming Language :: Python :: 2.7
Classifier: Programming Language :: Python :: 3
